IISRapi/__init__.py
IISRapi/data.py
IISRapi/dataset.py
IISRapi/model.py
IISRapi/tool.py
IISRapi/utils.py
IISRapi-2.1.4.dist-info/LICENSE
IISRapi-2.1.4.dist-info/METADATA
IISRapi-2.1.4.dist-info/WHEEL
IISRapi-2.1.4.dist-info/top_level.txt
IISRapi-2.1.4.dist-info/RECORD
