Metadata-Version: 2.1
Name: IISRapi
Version: 2.1.4
License: MIT
License-File: LICENSE
Requires-Dist: transformers
Requires-Dist: flair
Requires-Dist: torch
